{
  "domain": "shellcipm-proxy.onrender.com",
  "clientId": "FeVF2xXNARNb0W1GGgQ2y7I4ZeBIWzdb",
  "audience": "https://demo.okta.com",
  "auth0Domain": "shelldemo.cic-demo-platform.auth0app.com",
  "auth0": {
    "issuerBaseURL": "https://shelldemo.oktademo.cloud/"
  },
  "journeyConfig": {
    "email1": {
      "clientId": "FeVF2xXNARNb0W1GGgQ2y7I4ZeBIWzdb",
      "domain": "shellcipm-proxy.onrender.com"
    },
    "email22": {
      "clientId": "CE4GY2dAUwKvQi7FlCBrq9NynP2bCUci",
      "domain": "shelldemo.oktademo.cloud",
      "apiUrl": "http://localhost:3001/api"
    },
    "sniper_link": {
      "clientId": "Xp0v4LI2HebrEWV9gV5WylyRkejP3joP",
      "domain": "shelldemo.oktademo.cloud"
    },
    "2sv_optional": {
      "clientId": "5YNCvkd2lbFy3d0nrCcTuvaAiXaxfth1",
      "domain": "shelldemo.oktademo.cloud"
    },
    "2sv_mandatory": {
      "clientId": "g2LYYGxKwhQcnOqxQ0ylkSPryus7uGYD",
      "domain": "shelldemo.oktademo.cloud"
    },
    "sms_otp": {
      "clientId": "JXMBGR7zly8SloB16U7hsHOCBTTyBW0T",
      "domain": "shelldemo.oktademo.cloud"
    },
    "phone_password": {
      "clientId": "vl8qfNKq3vIllCQ0Wdjlcy52jgQ0viFM",
      "domain": "shelldemo.oktademo.cloud"
    },
    "invite": {
      "clientId": "idM0BINRTdeMuUKsTw00U5vRmojFRGcP",
      "domain": "shelldemo.oktademo.cloud",
      "authorizationParams": {
        "organization": "org_RFN4BI4eiF1RwGjW"
      }
    },
    "sms_invite": {
      "clientId": "S0JEM4iyNyyF8XFqnnembY9NFRe4r46H",
      "domain": "shelldemo.oktademo.cloud"
    }
  },
  "apiUrl": "https://shellcipm-middleware.onrender.com/api"
}

